{
	"type": "Attack",
	"class": null,
	"cp": 3,
	"at": 5,
	"element": "Electric",
	"field": "010010010",
	"effect": "",
	"icon": null,
	"pins": "01100000124",
	"notes": "",
	"releases": {
		"jp": {
			"name": "\u30b5\u30f3\u30c0\u30fc\u30de\u30f3\uff33\uff30",
			"set": null,
			"front": {
				"image": "237-\u30b5\u30f3\u30c0\u30fc\u30de\u30f3\uff33\uff30.jpg",
				"credits": "Image courtesy of suruga-ya.jp"
			},
			"back": {
				"image": null,
				"credits": null
			},
			"official": true,
			"notes": ""
		},
		"en": {
			"name": "ThunderManSP",
			"set": null,
			"front": {
				"image": null,
				"credits": null
			},
			"back": {
				"image": null,
				"credits": null
			},
			"official": false,
			"notes": ""
		}
	}
}