{
	"type": "Attack",
	"class": null,
	"cp": 9,
	"at": 12,
	"element": "Neutral",
	"field": "110110110",
	"effect": "",
	"icon": null,
	"pins": "01100010124",
	"notes": "",
	"releases": {
		"jp": {
			"name": "\u30d6\u30eb\u30fc\u30b9\uff24\uff33",
			"set": null,
			"front": {
				"image": "241-\u30d6\u30eb\u30fc\u30b9\uff24\uff33.jpg",
				"credits": "Image courtesy of suruga-ya.jp"
			},
			"back": {
				"image": null,
				"credits": null
			},
			"official": true,
			"notes": ""
		},
		"en": {
			"name": "ProtoManDS",
			"set": null,
			"front": {
				"image": null,
				"credits": null
			},
			"back": {
				"image": null,
				"credits": null
			},
			"official": false,
			"notes": ""
		}
	}
}