{
	"type": "Attack",
	"class": null,
	"cp": 2,
	"at": 3,
	"element": "Neutral",
	"field": "101010101",
	"effect": "",
	"icon": null,
	"pins": "01101010124",
	"notes": "",
	"releases": {
		"jp": {
			"name": "\u30bf\u30c3\u30d7\u30de\u30f3",
			"set": null,
			"front": {
				"image": "257-\u30bf\u30c3\u30d7\u30de\u30f3 (bad).jpg",
				"credits": "Image courtesy of FlashManEXE"
			},
			"back": {
				"image": null,
				"credits": null
			},
			"official": true,
			"notes": ""
		},
		"en": {
			"name": "TopMan",
			"set": null,
			"front": {
				"image": null,
				"credits": null
			},
			"back": {
				"image": null,
				"credits": null
			},
			"official": false,
			"notes": ""
		}
	}
}